german_privacy_shield/__init__.py
german_privacy_shield/cli.py
german_privacy_shield/client.py
german_privacy_shield/knowledge_base.py
german_privacy_shield-0.1.0.dist-info/METADATA
german_privacy_shield-0.1.0.dist-info/WHEEL
german_privacy_shield-0.1.0.dist-info/entry_points.txt
german_privacy_shield-0.1.0.dist-info/top_level.txt
german_privacy_shield-0.1.0.dist-info/RECORD
