Metadata-Version: 2.4
Name: german-privacy-shield
Version: 0.1.0
Summary: DSGVO-konforme Dokument-Redaktion mit KI - Erkennt und schwärzt personenbezogene Daten
Author-email: Keyvan Hardani <info@keyvan.ai>
Maintainer-email: Keyvan Hardani <info@keyvan.ai>
License: Apache-2.0
Project-URL: Homepage, https://github.com/Keyvanhardani/german-privacy-shield
Project-URL: Documentation, https://github.com/Keyvanhardani/german-privacy-shield#readme
Project-URL: Repository, https://github.com/Keyvanhardani/german-privacy-shield
Project-URL: Issues, https://github.com/Keyvanhardani/german-privacy-shield/issues
Keywords: dsgvo,gdpr,privacy,pii,redaction,ocr,document,german,ai,ollama,qwen
Classifier: Development Status :: 4 - Beta
Classifier: Intended Audience :: Developers
Classifier: Intended Audience :: Legal Industry
Classifier: Intended Audience :: Financial and Insurance Industry
Classifier: License :: OSI Approved :: Apache Software License
Classifier: Operating System :: OS Independent
Classifier: Programming Language :: Python :: 3
Classifier: Programming Language :: Python :: 3.9
Classifier: Programming Language :: Python :: 3.10
Classifier: Programming Language :: Python :: 3.11
Classifier: Programming Language :: Python :: 3.12
Classifier: Topic :: Security
Classifier: Topic :: Text Processing :: General
Classifier: Topic :: Scientific/Engineering :: Artificial Intelligence
Classifier: Natural Language :: German
Requires-Python: >=3.9
Requires-Dist: ollama>=0.1.0
Requires-Dist: Pillow>=9.0.0
Provides-Extra: dev
Requires-Dist: pytest>=7.0.0; extra == "dev"
Requires-Dist: pytest-cov>=4.0.0; extra == "dev"
Requires-Dist: black>=23.0.0; extra == "dev"
Requires-Dist: isort>=5.0.0; extra == "dev"
Requires-Dist: mypy>=1.0.0; extra == "dev"
Provides-Extra: ocr
Requires-Dist: paddleocr>=2.7.0; extra == "ocr"
Requires-Dist: paddlepaddle>=2.5.0; extra == "ocr"
